Metadata-Version: 2.1
Name: wagtail-opengraph-image-generator
Version: 2.0
Summary: Wagtail addon to assist in creating Open Graph images for your pages
Home-page: https://github.com/candylabshq/wagtail-opengraph-image-generator
Author: Candylabs GmbH
Author-email: info@candylabs.de
License: MIT
Classifier: Programming Language :: Python :: 3
Classifier: License :: OSI Approved :: MIT License
Classifier: Operating System :: OS Independent
Classifier: Framework :: Django
Classifier: Framework :: Wagtail
Requires-Python: >=3.7
License-File: LICENSE
Requires-Dist: wagtail (<5.0,>=4.0)
Requires-Dist: CairoSVG (==2.7.0)
Requires-Dist: Pillow (==9.5.0)
Provides-Extra: doc
Requires-Dist: mkdocs ; extra == 'doc'
Requires-Dist: markdown-include ; extra == 'doc'
